dewy_client/__init__.py
dewy_client/api/__init__.py
dewy_client/api/kb/__init__.py
dewy_client/api/kb/add_collection.py
dewy_client/api/kb/add_document.py
dewy_client/api/kb/delete_collection.py
dewy_client/api/kb/delete_document.py
dewy_client/api/kb/get_chunk.py
dewy_client/api/kb/get_collection.py
dewy_client/api/kb/get_document.py
dewy_client/api/kb/get_document_status.py
dewy_client/api/kb/list_chunks.py
dewy_client/api/kb/list_collections.py
dewy_client/api/kb/list_documents.py
dewy_client/api/kb/retrieve_chunks.py
dewy_client/api/kb/upload_document_content.py
dewy_client/client.py
dewy_client/errors.py
dewy_client/models/__init__.py
dewy_client/models/add_document_request.py
dewy_client/models/body_upload_document_content.py
dewy_client/models/collection.py
dewy_client/models/collection_create.py
dewy_client/models/distance_metric.py
dewy_client/models/document.py
dewy_client/models/document_status.py
dewy_client/models/http_validation_error.py
dewy_client/models/image_chunk.py
dewy_client/models/image_result.py
dewy_client/models/ingest_state.py
dewy_client/models/retrieve_request.py
dewy_client/models/retrieve_response.py
dewy_client/models/text_chunk.py
dewy_client/models/text_result.py
dewy_client/models/validation_error.py
dewy_client/py.typed
dewy_client/types.py
dewy_client-0.4.0.dist-info/METADATA
dewy_client-0.4.0.dist-info/WHEEL
dewy_client-0.4.0.dist-info/RECORD
